<odoo>
  <data>
    <!-- Kanban de alumnos para profesores -->
    <record id="view_erasmus_alumnos_kanban" model="ir.ui.view">
      <field name="name">erasmus.alumnos.kanban</field>
      <field name="model">erasmus.persona</field>
      <field name="arch" type="xml">
        <kanban class="o_kanban_small_column" default_group_by="kanban_col_profesor"
                records_draggable="false" groups_draggable="false" group_create="false">
          <field name="active"/>
          <field name="image_1920"/>
          <field name="nombre"/>
          <field name="apellido1"/>
          <field name="apellido2"/>
          <field name="email"/>
          <field name="kanban_col_profesor"/>
          <field name="revision_estado"/>
          <field name="estado_documentacion"/>
          <field name="progreso_documentacion"/>
          <templates>
            <t t-name="kanban-box">
              <div class="oe_kanban_global_click o_kanban_record" style="position:relative;padding:0!important;margin:0 0 10px 0!important;border:1px solid rgba(0,0,0,.25)!important;background:#fff;overflow:hidden;">
                <t t-if="!record.active.raw_value">
                  <div class="ge-archived-overlay" style="position:absolute;inset:0;z-index:20;pointer-events:none;display:flex;align-items:flex-start;justify-content:flex-end;overflow:hidden;background:transparent;border:none;margin:0;padding:0;">
                    <img src="/gestion_erasmus/static/src/img/archived_overlay2.png" alt="Archivado" style="height:auto;width:auto;max-height:100%;max-width:45%;object-fit:contain;display:block;border:0;box-shadow:none;filter:none;background:transparent;margin:0;padding:0;"/>
                  </div>
                </t>
                <div style="display:flex;align-items:center;gap:12px;">
                  <div>
        <img t-if="record.image_1920.raw_value"
          t-att-src="kanban_image('erasmus.persona', 'image_1920', record.id.raw_value)"
          alt="Avatar"
          style="width:48px;height:48px;border-radius:50%;object-fit:cover;border:1px solid #eee;"/>
                    <div t-else="" style="width:48px;height:48px;border-radius:50%;background:#f3f4f6;display:flex;align-items:center;justify-content:center;border:1px solid #eee;">👤</div>
                  </div>
                  <div style="flex:1;min-width:0;">
                    <div style="display:flex;align-items:center;gap:8px;flex-wrap:wrap;">
                      <strong style="font-size:14px;" t-esc="(record.nombre.value || '') + ' ' + (record.apellido1.value || '') + (record.apellido2.value ? (' ' + record.apellido2.value) : '')"/>
                    </div>
                    <div t-if="record.email.raw_value" class="o_text_muted" style="font-size:12px;" t-esc="record.email.value"/>
                    <div style="display:flex;align-items:center;gap:8px;margin-top:8px;">
                      <div style="flex:1;">
                        <field name="progreso_documentacion" widget="progressbar" options="{'max_value': 100}"/>
                      </div>
                      <span t-attf-class="badge #{record.estado_documentacion.raw_value === 'completo' ? 'text-bg-success' : (record.estado_documentacion.raw_value === 'en_proceso' ? 'text-bg-warning' : 'text-bg-secondary')}" t-esc="record.estado_documentacion.value or ''"/>
                      <span t-if="record.revision_estado.value" class="badge text-bg-info" t-esc="record.revision_estado.value"/>
                    </div>
                  </div>
                </div>
              </div>
            </t>
          </templates>
        </kanban>
      </field>
    </record>

        <!-- Eliminado: vista heredada de corrección del botón de informe.
             Motivo: usaba selectores no permitidos (atributo @string) que provocaban ParseError en la carga del módulo.
             El formulario base ya define el botón correcto para generar el PDF (type="action" name="%(report_gestion_erasmus_contrato_persona)d"). -->


    <!-- Kanban View (Profesional con tarjetas y sin arrastrar) -->
    <record id="view_erasmus_persona_kanban" model="ir.ui.view">
      <field name="name">erasmus.persona.kanban</field>
      <field name="model">erasmus.persona</field>
      <field name="arch" type="xml">
        <kanban default_group_by="tipo_interno" class="o_kanban_small_column"
                records_draggable="false" groups_draggable="false" group_create="false">
          <field name="active"/>
          <field name="image_1920"/>
          <field name="nombre"/>
          <field name="apellido1"/>
          <field name="apellido2"/>
          <field name="tipo_interno"/>
          <field name="email"/>
          <templates>
            <t t-name="kanban-box">
              <div class="oe_kanban_global_click o_kanban_record" style="position:relative;padding:0!important;margin:0 0 10px 0!important;border:1px solid rgba(0,0,0,.25)!important;background:#fff;overflow:hidden;">
                <t t-if="!record.active.raw_value">
                  <div class="ge-archived-overlay" style="position:absolute;inset:0;z-index:20;pointer-events:none;display:flex;align-items:flex-start;justify-content:flex-end;overflow:hidden;background:transparent;border:none;margin:0;padding:0;">
                    <img src="/gestion_erasmus/static/src/img/archived_overlay2.png" alt="Archivado" style="height:auto;width:auto;max-height:100%;max-width:45%;object-fit:contain;display:block;border:0;box-shadow:none;filter:none;background:transparent;margin:0;padding:0;"/>
                  </div>
                </t>
                <div style="display:flex;align-items:center;gap:12px;">
                  <div>
        <img t-if="record.image_1920.raw_value"
          t-att-src="kanban_image('erasmus.persona', 'image_1920', record.id.raw_value)"
          alt="Avatar"
          style="width:48px;height:48px;border-radius:50%;object-fit:cover;border:1px solid #eee;"/>
                    <div t-else="" style="width:48px;height:48px;border-radius:50%;background:#f3f4f6;display:flex;align-items:center;justify-content:center;border:1px solid #eee;">👤</div>
                  </div>
                  <div style="flex:1;min-width:0;">
                    <div style="display:flex;align-items:center;gap:8px;flex-wrap:wrap;">
                      <strong style="font-size:14px;" t-esc="(record.nombre.value || '') + ' ' + (record.apellido1.value || '') + (record.apellido2.value ? (' ' + record.apellido2.value) : '')"/>
                    </div>
                    <div t-if="record.email.raw_value" class="o_text_muted" style="font-size:12px;" t-esc="record.email.value"/>
                  </div>
                </div>
              </div>
            </t>
          </templates>
        </kanban>
      </field>
    </record>


    <!-- Kanban de borradores para Admin, agrupado por estado de revisión -->
    <record id="view_erasmus_borradores_kanban" model="ir.ui.view">
      <field name="name">erasmus.borradores.kanban</field>
      <field name="model">erasmus.persona</field>
      <field name="arch" type="xml">
        <kanban class="o_kanban_small_column" default_group_by="revision_estado"
                records_draggable="false" groups_draggable="false" group_create="false">
          <field name="active"/>
          <field name="image_1920"/>
          <field name="nombre"/>
          <field name="apellido1"/>
          <field name="apellido2"/>
          <field name="email"/>
          <field name="revision_estado"/>
          <field name="progreso_documentacion"/>
          <templates>
            <t t-name="kanban-box">
              <div class="oe_kanban_global_click o_kanban_record" style="position:relative;padding:0!important;margin:0 0 10px 0!important;border:1px solid rgba(0,0,0,.25)!important;background:#fff;overflow:hidden;">
                <t t-if="!record.active.raw_value">
                  <div class="ge-archived-overlay" style="position:absolute;inset:0;z-index:20;pointer-events:none;display:flex;align-items:flex-start;justify-content:flex-end;overflow:hidden;background:transparent;border:none;margin:0;padding:0;">
                    <img src="/gestion_erasmus/static/src/img/archived_overlay2.png" alt="Archivado" style="height:auto;width:auto;max-height:100%;max-width:45%;object-fit:contain;display:block;border:0;box-shadow:none;filter:none;background:transparent;margin:0;padding:0;"/>
                  </div>
                </t>
                <div style="display:flex;align-items:center;gap:12px;">
                  <div>
        <img t-if="record.image_1920.raw_value"
          t-att-src="kanban_image('erasmus.persona', 'image_1920', record.id.raw_value)"
          alt="Avatar"
          style="width:48px;height:48px;border-radius:50%;object-fit:cover;border:1px solid #eee;"/>
                    <div t-else="" style="width:48px;height:48px;border-radius:50%;background:#f3f4f6;display:flex;align-items:center;justify-content:center;border:1px solid #eee;">👤</div>
                  </div>
                  <div style="flex:1;min-width:0;">
                    <div style="display:flex;align-items:center;gap:8px;flex-wrap:wrap;">
                      <strong style="font-size:14px;" t-esc="(record.nombre.value || '') + ' ' + (record.apellido1.value || '') + (record.apellido2.value ? (' ' + record.apellido2.value) : '')"/>
                    </div>
                    <div t-if="record.email.raw_value" class="o_text_muted" style="font-size:12px;" t-esc="record.email.value"/>
                    <div style="display:flex;align-items:center;gap:8px;margin-top:8px;">
                      <div style="flex:1;">
                        <field name="progreso_documentacion" widget="progressbar" options="{'max_value': 100}"/>
                      </div>
                      <span t-if="record.revision_estado.value" class="badge" t-attf-class="badge #{record.revision_estado.raw_value === 'enviado' ? 'text-bg-secondary' : (record.revision_estado.raw_value === 'en_revision' ? 'text-bg-warning' : 'text-bg-success')}">
                        <t t-esc="record.revision_estado.value"/>
                      </span>
                    </div>
                  </div>
                </div>
              </div>
            </t>
          </templates>
        </kanban>
      </field>
    </record>

  </data>
</odoo>
